jiav_ansible/__init__.py
jiav_ansible/backend.py
jiav_ansible/py.typed
jiav_backend_ansible-0.2.0.dist-info/METADATA
jiav_backend_ansible-0.2.0.dist-info/WHEEL
jiav_backend_ansible-0.2.0.dist-info/entry_points.txt
jiav_backend_ansible-0.2.0.dist-info/RECORD
